python_probabilities/__init__.py
python_probabilities/distributions_binomial.py
python_probabilities/distributions_geometric.py
python_probabilities/distributions_normal.py
python_probabilities/distributions_poisson.py
python_probabilities-0.4.3.dist-info/LICENSE
python_probabilities-0.4.3.dist-info/METADATA
python_probabilities-0.4.3.dist-info/WHEEL
python_probabilities-0.4.3.dist-info/RECORD
