Metadata-Version: 2.1
Name: python-probabilities
Version: 0.4.3
Summary: Library for accurate statistical calculations using Python.
Author: berkay-yalin
Author-email: 66202981+berkay-yalin@users.noreply.github.com
Requires-Python: >=3.9,<4.0
Classifier: Programming Language :: Python :: 3
Classifier: Programming Language :: Python :: 3.9
Classifier: Programming Language :: Python :: 3.10
Classifier: Programming Language :: Python :: 3.11
